.gitignore
CHANGES.txt
CONTRIBUTORS.txt
README.rst
bootstrap.py
buildout.cfg
setup.py
docs/LICENSE.GPL
docs/LICENSE.txt
src/Products/__init__.py
src/Products.CallProfiler.egg-info/PKG-INFO
src/Products.CallProfiler.egg-info/SOURCES.txt
src/Products.CallProfiler.egg-info/dependency_links.txt
src/Products.CallProfiler.egg-info/entry_points.txt
src/Products.CallProfiler.egg-info/namespace_packages.txt
src/Products.CallProfiler.egg-info/not-zip-safe
src/Products.CallProfiler.egg-info/requires.txt
src/Products.CallProfiler.egg-info/top_level.txt
src/Products/CallProfiler/CallProfiler.py
src/Products/CallProfiler/CallProfiler.py.orig
src/Products/CallProfiler/TODO.txt
src/Products/CallProfiler/__init__.py
src/Products/CallProfiler/configure.zcml
src/Products/CallProfiler/profiler.py
src/Products/CallProfiler/refresh.txt
src/Products/CallProfiler/run_tests
src/Products/CallProfiler/dtml/aggregateDetail.dtml
src/Products/CallProfiler/dtml/aggregates.dtml
src/Products/CallProfiler/dtml/configure.dtml
src/Products/CallProfiler/dtml/detail.dtml
src/Products/CallProfiler/dtml/results.dtml
src/Products/CallProfiler/dtml/resultsByURL.dtml
src/Products/CallProfiler/test/__init__.py
src/Products/CallProfiler/test/test_profiler.py
src/Products/CallProfiler/www/profiler.gif