Metadata-Version: 1.0
Name: Products.CallProfiler
Version: 1.5.2
Summary: Call Profiler monitors the chain of DTML, ZSQL, ZPT, Python method and Python Script
Home-page: http://github.com/collective/Products.CallProfiler
Author: Richard Jones
Author-email: product-developers@lists.plone.org
License: gpl
Platform: UNKNOWN
Classifier: Programming Language :: Python
